aes_pkcs5/__init__.py
aes_pkcs5/algorithms/__init__.py
aes_pkcs5/algorithms/aes_cbc_pkcs5_padding.py
aes_pkcs5/algorithms/aes_ecb_pkcs5_padding.py
aes_pkcs5-1.0.4.dist-info/METADATA
aes_pkcs5-1.0.4.dist-info/WHEEL
aes_pkcs5-1.0.4.dist-info/licenses/LICENSE
aes_pkcs5-1.0.4.dist-info/RECORD
