Metadata-Version: 2.4
Name: aes_pkcs5
Version: 1.0.4
Summary: Implementation of AES with CBC/ECB mode and padding scheme PKCS5
Project-URL: Documentation, https://aes-pkcs5.readthedocs.io
Project-URL: Source, https://github.com/Laerte/aes_pkcs5
Project-URL: Tracker, https://github.com/Laerte/aes_pkcs5/issues
Author-email: Laerte Pereira <hi@laerte.dev>
Maintainer-email: Laerte Pereira <hi@laerte.dev>
License-Expression: BSD-2-Clause
License-File: LICENSE
Classifier: Development Status :: 5 - Production/Stable
Classifier: Intended Audience :: Developers
Classifier: Operating System :: OS Independent
Classifier: Programming Language :: Python
Classifier: Programming Language :: Python :: 3
Classifier: Programming Language :: Python :: 3.9
Classifier: Programming Language :: Python :: 3.10
Classifier: Programming Language :: Python :: 3.11
Classifier: Programming Language :: Python :: 3.12
Classifier: Programming Language :: Python :: 3.13
Classifier: Programming Language :: Python :: Implementation :: CPython
Classifier: Programming Language :: Python :: Implementation :: PyPy
Classifier: Topic :: Software Development :: Libraries :: Python Modules
Requires-Python: >=3.9
Requires-Dist: cryptography>=41.0.2
Provides-Extra: dev
Requires-Dist: black>=23.7.0; extra == 'dev'
Requires-Dist: isort>=5.12.0; extra == 'dev'
Requires-Dist: pre-commit>=3.3.3; extra == 'dev'
